cadence/__init__.py
cadence/modeling_gemma3_punctuation.py
cadence/punctuation_model.py
cadence/utils.py
cadence_punctuation-1.0.5.dist-info/licenses/LICENSE
cadence_punctuation-1.0.5.dist-info/METADATA
cadence_punctuation-1.0.5.dist-info/WHEEL
cadence_punctuation-1.0.5.dist-info/top_level.txt
cadence_punctuation-1.0.5.dist-info/RECORD
