Metadata-Version: 2.4
Name: cadence-punctuation
Version: 1.0.5
Summary: Multilingual punctuation restoration model for Indic languages
Home-page: https://github.com/AI4Bharat/Cadence
Author: AI4Bhārat
Author-email: opensource@ai4bharat.org
Classifier: Development Status :: 4 - Beta
Classifier: Intended Audience :: Developers
Classifier: Intended Audience :: Science/Research
Classifier: License :: OSI Approved :: MIT License
Classifier: Operating System :: OS Independent
Classifier: Programming Language :: Python :: 3
Classifier: Programming Language :: Python :: 3.9
Classifier: Programming Language :: Python :: 3.10
Classifier: Programming Language :: Python :: 3.11
Classifier: Topic :: Scientific/Engineering :: Artificial Intelligence
Classifier: Topic :: Text Processing :: Linguistic
Requires-Python: >=3.9
License-File: LICENSE
Requires-Dist: torch>=2.1.0
Requires-Dist: transformers>=4.51.3
Requires-Dist: safetensors>=0.4.1
Requires-Dist: numpy>=1.21.0
Requires-Dist: huggingface-hub>=0.30.2
Dynamic: author
Dynamic: author-email
Dynamic: classifier
Dynamic: description
Dynamic: description-content-type
Dynamic: home-page
Dynamic: license-file
Dynamic: requires-dist
Dynamic: requires-python
Dynamic: summary
